yaplot/__init__.py
yaplot-0.0.1.dist-info/LICENSE
yaplot-0.0.1.dist-info/METADATA
yaplot-0.0.1.dist-info/WHEEL
yaplot-0.0.1.dist-info/top_level.txt
yaplot-0.0.1.dist-info/RECORD
