Metadata-Version: 2.1
Name: yaplot
Version: 0.0.1
Summary: Yet Another Python3 graph package
Home-page: https://github.com/dhkim09a/yaplot
Author: Donghwi Kim
Author-email: dhkim09a@gmail.com
License: UNKNOWN
Project-URL: Bug Tracker, https://github.com/dhkim09a/yaplot/issues
Platform: UNKNOWN
Classifier: Programming Language :: Python :: 3
Classifier: License :: OSI Approved :: MIT License
Classifier: Operating System :: OS Independent
Requires-Python: >=3.7
License-File: LICENSE
